odd/__init__.py
odd/is_odd.py
odd-1.0.1.dist-info/LICENSE
odd-1.0.1.dist-info/METADATA
odd-1.0.1.dist-info/WHEEL
odd-1.0.1.dist-info/RECORD
